traderusty-0.1.4.dist-info/METADATA
traderusty-0.1.4.dist-info/WHEEL
traderusty-0.1.4.dist-info/license_files/LICENSE.txt
traderusty/traderusty.pyi
traderusty/__init__.py
traderusty/traderusty.abi3.so
traderusty-0.1.4.dist-info/RECORD
